CHANGES.txt
README.txt
ZopePublicLicense.txt
bootstrap.py
buildout.cfg
setup.py
src/zc/__init__.py
src/zc.copy.egg-info/PKG-INFO
src/zc.copy.egg-info/SOURCES.txt
src/zc.copy.egg-info/dependency_links.txt
src/zc.copy.egg-info/namespace_packages.txt
src/zc.copy.egg-info/not-zip-safe
src/zc.copy.egg-info/requires.txt
src/zc.copy.egg-info/top_level.txt
src/zc/copy/__init__.py
src/zc/copy/configure.zcml
src/zc/copy/interfaces.py
src/zc/copy/overrides.zcml
src/zc/copy/tests.py