Metadata-Version: 1.0
Name: zc.copy
Version: 1.2
Summary: Pluggable object copying (deprecated in favor of zope.copy)
Home-page: UNKNOWN
Author: Zope Project
Author-email: zope-dev@zope.org
License: ZPL 2.1
Keywords: zope zope3 copy clone
Platform: UNKNOWN
